faker_wifi_essid/__init__.py
faker_wifi_essid/common_essids.py
faker_wifi_essid/wifi_essid.py
faker_wifi_essid-0.5.0.dist-info/LICENSE
faker_wifi_essid-0.5.0.dist-info/METADATA
faker_wifi_essid-0.5.0.dist-info/WHEEL
faker_wifi_essid-0.5.0.dist-info/top_level.txt
faker_wifi_essid-0.5.0.dist-info/RECORD
