Metadata-Version: 2.1
Name: faker_wifi_essid
Version: 0.5.0
Summary: Faker provider for Wi-Fi ESSIDs.
Author-email: Paul-Emmanuel Raoul <skyper@skyplabs.net>
Project-URL: Bug Tracker, https://github.com/SkypLabs/faker-wifi-essid/issues
Project-URL: Repository, https://github.com/SkypLabs/faker-wifi-essid
Keywords: faker,faker-library,faker-provider,faker-generator,wifi,essid
Classifier: Development Status :: 4 - Beta
Classifier: Intended Audience :: Developers
Classifier: Topic :: Software Development :: Libraries :: Python Modules
Classifier: Operating System :: OS Independent
Classifier: Programming Language :: Python :: 3 :: Only
Classifier: Programming Language :: Python :: 3.9
Classifier: Programming Language :: Python :: 3.10
Classifier: Programming Language :: Python :: 3.11
Classifier: Programming Language :: Python :: 3.12
Classifier: Programming Language :: Python :: 3.13
Classifier: License :: OSI Approved :: MIT License
Requires-Python: <4,>=3.9
License-File: LICENSE
Requires-Dist: Faker<34.0,>=4.1
Provides-Extra: dev
Requires-Dist: ruff; extra == "dev"
Provides-Extra: docs
Requires-Dist: Sphinx>=3.2; extra == "docs"
Requires-Dist: sphinx_rtd_theme>=0.5.0; extra == "docs"
Provides-Extra: tests
Requires-Dist: tox; extra == "tests"
